LICENSE
MANIFEST.in
README.rst
setup.py
awesome/__init__.py
awesome/foo.py
awesome/assets/who-is-awesome.jpg
awesome_package.egg-info/PKG-INFO
awesome_package.egg-info/SOURCES.txt
awesome_package.egg-info/dependency_links.txt
awesome_package.egg-info/not-zip-safe
awesome_package.egg-info/top_level.txt