Metadata-Version: 1.1
Name: awesome-package
Version: 1.10.2
Summary: Integrates the awesomeness
Home-page: https://bitbucket.org/tim_heap/python-packaging-101
Author: Tim Heap
Author-email: heap.tim@gmail.com
License: Unlicense
Platform: UNKNOWN
Classifier: Development Status :: 5 - Production/Stable
Classifier: Intended Audience :: Developers
Classifier: Operating System :: OS Independent
Classifier: Programming Language :: Python
